nereus/__init__.py
nereus/_version.py
nereus/core/__init__.py
nereus/core/coordinates.py
nereus/core/grids.py
nereus/core/types.py
nereus/diag/__init__.py
nereus/diag/hovmoller.py
nereus/diag/ice.py
nereus/diag/regions.py
nereus/diag/vertical.py
nereus/diag/data/MOCBasins.geojson
nereus/diag/data/NinoRegions.geojson
nereus/diag/data/oceanBasins.geojson
nereus/models/__init__.py
nereus/models/_base.py
nereus/models/fesom/__init__.py
nereus/models/fesom/mesh.py
nereus/models/healpix/__init__.py
nereus/models/icona/__init__.py
nereus/models/icono/__init__.py
nereus/models/ifs/__init__.py
nereus/plotting/__init__.py
nereus/plotting/maps.py
nereus/plotting/projections.py
nereus/plotting/transect.py
nereus/regrid/__init__.py
nereus/regrid/cache.py
nereus/regrid/interpolator.py
nereus-0.2.1.dist-info/METADATA
nereus-0.2.1.dist-info/WHEEL
nereus-0.2.1.dist-info/licenses/LICENSE
nereus-0.2.1.dist-info/RECORD
